cmmnbuild_dep_manager/__init__.py
cmmnbuild_dep_manager/__main__.py
cmmnbuild_dep_manager/_version.py
cmmnbuild_dep_manager/cmmnbuild_dep_manager.py
cmmnbuild_dep_manager/resolver/__init__.py
cmmnbuild_dep_manager/resolver/cbng_web.py
cmmnbuild_dep_manager/resolver/gradle-wrapper.zip
cmmnbuild_dep_manager/resolver/gradle.py
cmmnbuild_dep_manager/tests/__init__.py
cmmnbuild_dep_manager/tests/conftest.py
cmmnbuild_dep_manager/tests/test_Manager__load_modules.py
cmmnbuild_dep_manager/tests/test_cmmnbuild_dep_manager.py
cmmnbuild_dep_manager-2.5.0.dist-info/METADATA
cmmnbuild_dep_manager-2.5.0.dist-info/WHEEL
cmmnbuild_dep_manager-2.5.0.dist-info/top_level.txt
cmmnbuild_dep_manager-2.5.0.dist-info/RECORD
