Metadata-Version: 2.1
Name: cmmnbuild-dep-manager
Version: 2.5.0
Summary: Manages CERN's Java dependencies across multiple Python packages
Home-page: https://gitlab.cern.ch/scripting-tools/cmmnbuild-dep-manager
Maintainer: CERN Accelerating Python
Maintainer-email: acc-py-support@cern.ch
License: MIT
Platform: UNKNOWN
Classifier: Programming Language :: Python :: 3
Classifier: Operating System :: OS Independent
Requires-Python: >=3.6, <4
Requires-Dist: entrypoints
Requires-Dist: JPype1 (>=0.6.1)
Requires-Dist: requests
Requires-Dist: six
Provides-Extra: all
Requires-Dist: entrypoints ; extra == 'all'
Requires-Dist: JPype1 (>=0.6.1) ; extra == 'all'
Requires-Dist: requests ; extra == 'all'
Requires-Dist: six ; extra == 'all'
Requires-Dist: pytest ; extra == 'all'
Provides-Extra: core
Requires-Dist: entrypoints ; extra == 'core'
Requires-Dist: JPype1 (>=0.6.1) ; extra == 'core'
Requires-Dist: requests ; extra == 'core'
Requires-Dist: six ; extra == 'core'
Provides-Extra: dev
Requires-Dist: pytest ; extra == 'dev'
Provides-Extra: test
Requires-Dist: pytest ; extra == 'test'
